botibal/__init__.py
botibal/fukung.py
botibal/quizz.py
botibal/taunt.py
botibal/client/__init__.py
botibal/client/botibal_.py
botibal/client/cmd_parser.py
botibal/client/minibal.py
botibal/client/quizzibal.py
botibal/client/run.py
botibal-0.8.0.data/data/config/config.example.ini
botibal-0.8.0.dist-info/DESCRIPTION.rst
botibal-0.8.0.dist-info/METADATA
botibal-0.8.0.dist-info/RECORD
botibal-0.8.0.dist-info/WHEEL
botibal-0.8.0.dist-info/entry_points.txt
botibal-0.8.0.dist-info/metadata.json
botibal-0.8.0.dist-info/top_level.txt
