Metadata-Version: 2.0
Name: botibal
Version: 0.8.0
Summary: The silly, quizzical XMPP bot
Home-page: https://github.com/virtualtam/botibal
Author: VirtualTam
Author-email: virtualtam@flibidi.net
License: MIT
Keywords: bot jabber xmpp quizz chat
Platform: UNKNOWN
Classifier: Development Status :: 3 - Alpha
Classifier: Environment :: Console
Classifier: License :: OSI Approved :: MIT License
Classifier: Natural Language :: English
Classifier: Operating System :: POSIX :: Linux
Classifier: Programming Language :: Python :: 3
Classifier: Programming Language :: Python :: 3.4
Classifier: Programming Language :: Python :: 3.5
Classifier: Topic :: Communications :: Chat
Requires-Dist: pyasn1 (==0.1.9)
Requires-Dist: pyasn1-modules (==0.0.8)
Requires-Dist: slixmpp (==1.1)
Provides-Extra: DNS
Requires-Dist: dnspython (==1.12.0); extra == 'DNS'
